odoo/addons/hr_holidays_auto_extend/README.rst
odoo/addons/hr_holidays_auto_extend/__init__.py
odoo/addons/hr_holidays_auto_extend/__manifest__.py
odoo/addons/hr_holidays_auto_extend/data/cron.xml
odoo/addons/hr_holidays_auto_extend/data/mail.xml
odoo/addons/hr_holidays_auto_extend/i18n/hr_holidays_auto_extend.pot
odoo/addons/hr_holidays_auto_extend/i18n/it.po
odoo/addons/hr_holidays_auto_extend/models/__init__.py
odoo/addons/hr_holidays_auto_extend/models/hr_leave.py
odoo/addons/hr_holidays_auto_extend/models/hr_leave_type.py
odoo/addons/hr_holidays_auto_extend/readme/CONTRIBUTORS.rst
odoo/addons/hr_holidays_auto_extend/readme/DESCRIPTION.rst
odoo/addons/hr_holidays_auto_extend/readme/USAGE.rst
odoo/addons/hr_holidays_auto_extend/static/description/icon.png
odoo/addons/hr_holidays_auto_extend/static/description/index.html
odoo/addons/hr_holidays_auto_extend/tests/__init__.py
odoo/addons/hr_holidays_auto_extend/tests/test_extend.py
odoo/addons/hr_holidays_auto_extend/views/hr_leave.xml
odoo/addons/hr_holidays_auto_extend/views/hr_leave_type.xml
odoo14_addon_hr_holidays_auto_extend-14.0.1.0.1.dev4.dist-info/METADATA
odoo14_addon_hr_holidays_auto_extend-14.0.1.0.1.dev4.dist-info/WHEEL
odoo14_addon_hr_holidays_auto_extend-14.0.1.0.1.dev4.dist-info/top_level.txt
odoo14_addon_hr_holidays_auto_extend-14.0.1.0.1.dev4.dist-info/RECORD
